lems/__init__.py
lems/api.py
lems/run.py
lems/base/__init__.py
lems/base/base.py
lems/base/errors.py
lems/base/map.py
lems/base/stack.py
lems/base/util.py
lems/dlems/__init__.py
lems/dlems/exportdlems.py
lems/model/__init__.py
lems/model/component.py
lems/model/dynamics.py
lems/model/fundamental.py
lems/model/model.py
lems/model/simulation.py
lems/model/structure.py
lems/parser/LEMS.py
lems/parser/__init__.py
lems/parser/expr.py
lems/sim/__init__.py
lems/sim/build.py
lems/sim/recording.py
lems/sim/runnable.py
lems/sim/sim.py
pylems-0.6.8.dist-info/licenses/LICENSE.lesser
pylems-0.6.8.dist-info/METADATA
pylems-0.6.8.dist-info/WHEEL
pylems-0.6.8.dist-info/entry_points.txt
pylems-0.6.8.dist-info/top_level.txt
pylems-0.6.8.dist-info/RECORD
