Metadata-Version: 2.4
Name: PyLEMS
Version: 0.6.8
Summary: A Python library for working with the Low Entropy Model Specification language (LEMS)
Home-page: https://github.com/LEMS/pylems
Author: PyLEMS authors and contributors
Author-email: gautham@lisphacker.org, p.gleeson@gmail.com
Maintainer-email: p.gleeson@gmail.com
License: LGPL-3.0-only
Classifier: Intended Audience :: Science/Research
Classifier: License :: OSI Approved :: GNU Lesser General Public License v3 (LGPLv3)
Classifier: Natural Language :: English
Classifier: Operating System :: OS Independent
Classifier: Programming Language :: Python :: 3.8
Classifier: Programming Language :: Python :: 3.9
Classifier: Programming Language :: Python :: 3.10
Classifier: Programming Language :: Python :: 3.11
Classifier: Programming Language :: Python :: 3.12
Classifier: Programming Language :: Python :: 3.13
Classifier: Topic :: Scientific/Engineering
License-File: LICENSE.lesser
Requires-Dist: lxml
Requires-Dist: typing; python_version < "3.5"
Requires-Dist: matplotlib
Provides-Extra: doc
Requires-Dist: sphinxcontrib-bibtex; extra == "doc"
Provides-Extra: dev
Requires-Dist: pre-commit; extra == "dev"
Requires-Dist: ruff; extra == "dev"
Requires-Dist: pytest; extra == "dev"
Dynamic: license-file
